MANIFEST.in
README.md
setup.py
nobu/__init__.py
nobu/nobu.py
nobu.egg-info/PKG-INFO
nobu.egg-info/SOURCES.txt
nobu.egg-info/dependency_links.txt
nobu.egg-info/top_level.txt