Metadata-Version: 1.1
Name: nobu
Version: 1.0.4
Summary: A Library for turning a raspberry pi into a Server/Access Point
Home-page: https://github.com/sabzo/nobu
Author: @sabzo
Author-email: sabelo@sabelo.io
License: MIT
Keywords: raspberypi accesspoint wifi
Platform: UNKNOWN
Classifier: Development Status :: 5 - Production/Stable
Classifier: Intended Audience :: Developers
Classifier: Topic :: Software Development :: Libraries
Classifier: License :: OSI Approved :: MIT License
Classifier: Programming Language :: Python :: 2.7
Classifier: Programming Language :: Python :: 3
Classifier: Programming Language :: Python :: 3.3
Classifier: Programming Language :: Python :: 3.4
Classifier: Programming Language :: Python :: 3.5
